formvalidator/__init__.py
formvalidator/admin.py
formvalidator/apps.py
formvalidator/forms.py
formvalidator/models.py
formvalidator/settings.py
formvalidator/tests.py
formvalidator/urls.py
formvalidator/views.py
formvalidator/form_utils/__init__.py
formvalidator/form_utils/form_utils.py
formvalidator/migrations/__init__.py
formvalidator/static/formvalidator/js/forms.bundle.js
formvalidator/templates/base.html
formvalidator/templates/formvalidator/sample.html
formvalidator/templates/formvalidator/sample2.html
formvalidator/templates/includes/header.html
django_forms_frontend_validation-1.0.8.dist-info/LICENSE
django_forms_frontend_validation-1.0.8.dist-info/METADATA
django_forms_frontend_validation-1.0.8.dist-info/WHEEL
django_forms_frontend_validation-1.0.8.dist-info/top_level.txt
django_forms_frontend_validation-1.0.8.dist-info/RECORD
