Metadata-Version: 2.1
Name: django-forms-frontend-validation
Version: 1.0.8
Summary: A Django app for front-end form validation
Home-page: https://github.com/andrew-kyle92/django-forms-frontend-validation
Author: Andrew Kyle
Author-email: andrew.kyle92@yahoo.com
License: MIT
Classifier: Framework :: Django
Classifier: Programming Language :: Python
Classifier: License :: OSI Approved :: MIT License
License-File: LICENSE
Requires-Dist: Django>=3.2
